{"cameraMode":{"drawMode":0,"name":"Shaded","section":"Shading Mode"},"sceneLighting":true,"audioPlay":false,"sceneViewState":{"m_AlwaysRefresh":false,"showFog":true,"showSkybox":true,"showFlares":true,"showImageEffects":true,"showParticleSystems":true,"showVisualEffectGraphs":true,"m_FxEnabled":true},"in2DMode":false,"pivot":{"x":-1.0832233428955079,"y":0.557581901550293,"z":0.8357772827148438},"rotation":{"x":-0.08901704847812653,"y":0.8799232840538025,"z":-0.1823207587003708,"w":-0.42961764335632326},"size":8.269891738891602,"orthographic":false}